{
  "gitSyncId": "67d948f210ed5751471c0761_7795b447-d87c-46ce-8568-161527101672",
  "id": "Page1__$generate_ai_text1$_generate_ai_text",
  "isPublic": true,
  "moduleInstanceId": "Page1_generate_ai_text1",
  "pluginId": "Appsmith AI",
  "pluginType": "AI",
  "rootModuleInstanceId": "Page1_generate_ai_text1",
  "unpublishedAction": {
    "confirmBeforeExecute": false,
    "contextType": "PAGE",
    "datasource": {
      "datasourceConfiguration": {},
      "isAutoGenerated": false,
      "name": "DEFAULT_APPSMITH_AI_DATASOURCE",
      "pluginId": "Appsmith AI"
    },
    "executeOnLoad": true,
    "name": "_$generate_ai_text1$_generate_ai_text",
    "pageId": "Page1",
    "userSetOnLoad": false
  }
}